snowcrypt/__init__.py
snowcrypt/_version.py
snowcrypt/adrm_key_derivation.py
snowcrypt/constants.py
snowcrypt/localExceptions.py
snowcrypt/main.py
snowcrypt/myparser.py
snowcrypt/oldcrypt.py
snowcrypt/snowcrypt.py
snowcrypt/tinytag.py
snowcrypt-0.1.3.post0.dist-info/LICENSE
snowcrypt-0.1.3.post0.dist-info/METADATA
snowcrypt-0.1.3.post0.dist-info/WHEEL
snowcrypt-0.1.3.post0.dist-info/entry_points.txt
snowcrypt-0.1.3.post0.dist-info/top_level.txt
snowcrypt-0.1.3.post0.dist-info/RECORD
